{
  "metadata": {
    "title": "人力资源知识竞赛",
    "description": "快手HR游戏人力资源知识题库，涵盖快手招聘、员工福利、绩效考核、薪酬体系、文化建设等",
    "language": "zh-CN",
    "total_questions": 120,
    "difficulty_distribution": {
      "easy": 40,
      "medium": 40,
      "hard": 40
    },
    "created_at": "2026-07-06"
  },
  "questions": {
    "easy": [
      {
        "id": "E01",
        "question": "快手为员工提供的保险福利是？",
        "options": [
          "六险一金",
          "五险一金",
          "五险二金",
          "七险一金"
        ],
        "answer": "六险一金",
        "explanation": "快手提供六险一金，比法定五险一金多一份补充保险。"
      },
      {
        "id": "E02",
        "question": "快手每天的餐标是多少钱？",
        "options": [
          "80元",
          "100元",
          "120元",
          "150元"
        ],
        "answer": "120元",
        "explanation": "快手餐标为120元每人每天。"
      },
      {
        "id": "E03",
        "question": "快手每月的团建费用是多少？",
        "options": [
          "100元",
          "150元",
          "250元",
          "500元"
        ],
        "answer": "250元",
        "explanation": "快手团建费为250元每人每月。"
      },
      {
        "id": "E04",
        "question": "快手租房补贴的金额是？",
        "options": [
          "500元/月",
          "800元/月",
          "1000元/月",
          "1500元/月"
        ],
        "answer": "1000元/月",
        "explanation": "快手提供1000元/月的租房补贴。"
      },
      {
        "id": "E05",
        "question": "快手员工几点以后打车可以报销？",
        "options": [
          "9点后",
          "10点后",
          "11点后",
          "12点后"
        ],
        "answer": "10点后",
        "explanation": "快手规定10点后打车可报销。"
      },
      {
        "id": "E06",
        "question": "快手派价值观的核心理念是什么？",
        "options": [
          "痴迷客户",
          "创新务实",
          "最高标准",
          "担当敢为"
        ],
        "answer": "痴迷客户",
        "explanation": "快手派价值观核心理念：痴迷客户。"
      },
      {
        "id": "E07",
        "question": "OKR中的KR代表什么？",
        "options": [
          "Key Results（关键结果）",
          "Key Resources（关键资源）",
          "Key Requirements（关键需求）",
          "Key Reports（关键报告）"
        ],
        "answer": "Key Results（关键结果）",
        "explanation": "OKR = Objectives and Key Results，KR是衡量目标达成程度的关键结果。"
      },
      {
        "id": "E08",
        "question": "HRBP中的BP代表什么？",
        "options": [
          "Business Partner（业务伙伴）",
          "Business Plan（商业计划）",
          "Best Practice（最佳实践）",
          "Business Process（业务流程）"
        ],
        "answer": "Business Partner（业务伙伴）",
        "explanation": "HRBP = Human Resources Business Partner，即人力资源业务伙伴。"
      },
      {
        "id": "E09",
        "question": "快手为员工提供的购房福利是？",
        "options": [
          "无息贷款",
          "低息贷款",
          "购房补贴",
          "住房公积金"
        ],
        "answer": "无息贷款",
        "explanation": "快手为入职1年以上的员工提供购房无息贷款。"
      },
      {
        "id": "E10",
        "question": "快手购房无息贷款的申请条件是？",
        "options": [
          "入职1年以上",
          "入职3年以上",
          "任何时间均可",
          "仅限高管"
        ],
        "answer": "入职1年以上",
        "explanation": "购房无息贷款需入职满1年以上方可申请。"
      },
      {
        "id": "E11",
        "question": "劳动法规定的标准工时为每周不超过多少小时？",
        "options": [
          "40小时",
          "44小时",
          "48小时",
          "36小时"
        ],
        "answer": "40小时",
        "explanation": "劳动法规定每日不超过8小时，每周不超过40小时。"
      },
      {
        "id": "E12",
        "question": "法定试用期的最长时间是？",
        "options": [
          "6个月",
          "3个月",
          "1个月",
          "12个月"
        ],
        "answer": "6个月",
        "explanation": "劳动合同法规定三年以上合同试用期最长不超过6个月。"
      },
      {
        "id": "E13",
        "question": "快手派中'坦诚清晰'属于哪个维度？",
        "options": [
          "相处之道",
          "核心理念",
          "成事之法",
          "独立维度"
        ],
        "answer": "相处之道",
        "explanation": "坦诚清晰属于'相处之道'，与担当敢为并列。"
      },
      {
        "id": "E14",
        "question": "快手免费提供的健身设施是？",
        "options": [
          "免费健身房",
          "付费健身房",
          "仅户外运动",
          "无健身设施"
        ],
        "answer": "免费健身房",
        "explanation": "快手为员工提供免费健身房。"
      },
      {
        "id": "E15",
        "question": "'100%合规培训'的含义是？",
        "options": [
          "所有员工必须完成合规培训，覆盖率100%",
          "培训内容100%合规",
          "培训时长100小时",
          "考试成绩100分"
        ],
        "answer": "所有员工必须完成合规培训，覆盖率100%",
        "explanation": "100%合规培训要求全员完成，确保每位员工都了解合规要求。"
      },
      {
        "id": "E16",
        "question": "EAP的全称是什么？",
        "options": [
          "Employee Assistance Program（员工帮助计划）",
          "Enterprise Application Platform",
          "Employee Assessment Process",
          "Education Advancement Program"
        ],
        "answer": "Employee Assistance Program（员工帮助计划）",
        "explanation": "EAP是员工帮助计划，为员工提供心理咨询、法律援助等支持服务。"
      },
      {
        "id": "E17",
        "question": "快手派价值观中'创新务实'属于哪个维度？",
        "options": [
          "成事之法",
          "核心理念",
          "相处之道",
          "独立维度"
        ],
        "answer": "成事之法",
        "explanation": "创新务实属于'成事之法'，与最高标准并列。"
      },
      {
        "id": "E18",
        "question": "'人才盘点'的主要目的是？",
        "options": [
          "评估组织人才现状，识别关键人才和缺口",
          "清点办公设备",
          "统计员工数量",
          "核算薪资成本"
        ],
        "answer": "评估组织人才现状，识别关键人才和缺口",
        "explanation": "人才盘点是系统性评估组织人才现状，为人才发展决策提供依据。"
      },
      {
        "id": "E19",
        "question": "KPI的全称是什么？",
        "options": [
          "Key Performance Indicator",
          "Key Product Index",
          "Knowledge Process Integration",
          "Key Priority Item"
        ],
        "answer": "Key Performance Indicator",
        "explanation": "KPI = Key Performance Indicator，即关键绩效指标。"
      },
      {
        "id": "E20",
        "question": "快手派中'担当敢为'属于哪个维度？",
        "options": [
          "相处之道",
          "核心理念",
          "成事之法",
          "独立维度"
        ],
        "answer": "相处之道",
        "explanation": "担当敢为属于'相处之道'，与坦诚清晰并列。"
      },
      {
        "id": "E21",
        "question": "'校招'和'社招'的主要区别是？",
        "options": [
          "校招面向在校生，社招面向有工作经验者",
          "校招薪资更高",
          "社招不需要面试",
          "校招只招管理层"
        ],
        "answer": "校招面向在校生，社招面向有工作经验者",
        "explanation": "校招（校园招聘）面向应届毕业生，社招（社会招聘）面向有工作经验的人才。"
      },
      {
        "id": "E22",
        "question": "试用期解除劳动合同的法定条件是？",
        "options": [
          "证明不符合录用条件",
          "员工主动辞职",
          "公司经营困难",
          "员工请病假"
        ],
        "answer": "证明不符合录用条件",
        "explanation": "试用期解除需证明员工不符合录用条件，否则属于违法解除。"
      },
      {
        "id": "E23",
        "question": "快手下午茶福利的内容是什么？",
        "options": [
          "工作日下午提供茶点零食",
          "下午额外休息1小时",
          "下午茶话会活动",
          "下午折扣餐饮"
        ],
        "answer": "工作日下午提供茶点零食",
        "explanation": "快手为员工提供下午茶，在工作日下午供应茶点和零食。"
      },
      {
        "id": "E24",
        "question": "'入职流程'中，新员工入职第一天通常需要完成什么？",
        "options": [
          "办理入职手续、签署合同、了解公司制度",
          "直接开始工作",
          "参加年假",
          "无需任何手续"
        ],
        "answer": "办理入职手续、签署合同、了解公司制度",
        "explanation": "入职第一天需完成合同签署、工卡办理、制度学习等基础流程。"
      },
      {
        "id": "E25",
        "question": "'员工关系'管理的核心目标是？",
        "options": [
          "建立和维护良好的雇佣关系，预防和解决劳动纠纷",
          "控制员工数量",
          "监督员工工作",
          "管理员工社交媒体"
        ],
        "answer": "建立和维护良好的雇佣关系，预防和解决劳动纠纷",
        "explanation": "员工关系管理关注雇佣双方关系的健康和谐，处理纠纷、沟通和合规。"
      },
      {
        "id": "E26",
        "question": "快手派的'最高标准'属于哪个维度？",
        "options": [
          "成事之法",
          "核心理念",
          "相处之道",
          "独立维度"
        ],
        "answer": "成事之法",
        "explanation": "最高标准属于'成事之法'，与创新务实并列。"
      },
      {
        "id": "E27",
        "question": "六险一金中的'一金'指的是？",
        "options": [
          "住房公积金",
          "养老金",
          "违约金",
          "公积金（企业年金）"
        ],
        "answer": "住房公积金",
        "explanation": "一金指住房公积金，是法定的住房储金制度。"
      },
      {
        "id": "E28",
        "question": "'团队建设'活动的主要目的是？",
        "options": [
          "增强团队凝聚力和协作能力",
          "完成工作任务",
          "评估绩效",
          "招聘新人"
        ],
        "answer": "增强团队凝聚力和协作能力",
        "explanation": "团队建设活动通过共同体验增强信任、沟通和协作。"
      },
      {
        "id": "E29",
        "question": "'文化建设'在快手的核心载体是什么？",
        "options": [
          "快手派价值观体系",
          "员工手册",
          "办公环境",
          "年会上墙标语"
        ],
        "answer": "快手派价值观体系",
        "explanation": "快手派价值观体系是快手文化建设的核心载体和行动准则。"
      },
      {
        "id": "E30",
        "question": "'离职管理'中，'离职面谈'的主要目的是？",
        "options": [
          "强制挽留员工留下",
          "了解离职原因，收集改进建议",
          "办理社保和公积金转移",
          "评估员工绩效并追究责任"
        ],
        "answer": "了解离职原因，收集改进建议",
        "explanation": "离职面谈是获取真实反馈的重要渠道，帮助组织发现问题并改进。"
      },
      {
        "id": "E31",
        "question": "劳动合同法规定，用人单位自用工之日起超过一个月不满一年未签合同的后果是？",
        "options": [
          "向劳动者每月支付二倍工资",
          "补签合同即可",
          "无后果",
          "支付一个月工资"
        ],
        "answer": "向劳动者每月支付二倍工资",
        "explanation": "劳动合同法第82条规定，超1个月未签合同需支付二倍工资。"
      },
      {
        "id": "E32",
        "question": "'股权激励'的主要目的是？",
        "options": [
          "将员工利益与公司长期发展绑定，激励核心人才",
          "降低薪资成本",
          "减少员工数量",
          "替代社保缴纳"
        ],
        "answer": "将员工利益与公司长期发展绑定，激励核心人才",
        "explanation": "股权激励通过期权/限制性股票等让员工分享公司成长收益，实现利益一致。"
      },
      {
        "id": "E33",
        "question": "'员工满意度调查'的主要用途是？",
        "options": [
          "了解员工对工作各方面的满意程度，指导管理改善",
          "决定升职名单",
          "计算薪资",
          "考核绩效"
        ],
        "answer": "了解员工对工作各方面的满意程度，指导管理改善",
        "explanation": "员工满意度调查帮助组织识别管理问题和员工需求，驱动改善行动。"
      },
      {
        "id": "E34",
        "question": "劳动法规定的年假天数与什么因素相关？",
        "options": [
          "累计工作年限",
          "入职公司时间",
          "职位级别",
          "薪资水平"
        ],
        "answer": "累计工作年限",
        "explanation": "带薪年假天数根据累计工作年限确定：1-10年5天，10-20年10天，20年以上15天。"
      },
      {
        "id": "E35",
        "question": "'外包人员管理'中，外包员工与正式员工的主要区别是？",
        "options": [
          "外包员工工作满一年自动转为正式员工",
          "外包员工薪资一定更高",
          "外包员工与外包公司签合同，与用工单位无直接劳动关系的",
          "外包员工不需要遵守用工单位的制度"
        ],
        "answer": "外包员工与外包公司签合同，与用工单位无直接劳动关系的",
        "explanation": "外包员工与外包公司建立劳动关系，用工单位通过外包公司使用其劳务。"
      },
      {
        "id": "E36",
        "question": "快手上市的时间和交易所是？",
        "options": [
          "2021年2月5日，港交所",
          "2020年，上交所",
          "2022年，纽交所",
          "2019年，深交所"
        ],
        "answer": "2021年2月5日，港交所",
        "explanation": "快手2021年2月5日在港交所上市，股票代码01024。"
      },
      {
        "id": "E37",
        "question": "'薪酬体系'中，基本工资和绩效工资的关系通常是？",
        "options": [
          "基本工资固定保障，绩效工资随业绩浮动",
          "两者都固定",
          "两者都浮动",
          "基本工资浮动，绩效固定"
        ],
        "answer": "基本工资固定保障，绩效工资随业绩浮动",
        "explanation": "基本工资提供稳定收入保障，绩效工资与个人/团队/公司业绩挂钩，浮动激励。"
      },
      {
        "id": "E38",
        "question": "'绩效考核'的常见周期是？",
        "options": [
          "季度或半年度",
          "每年一次",
          "每月一次",
          "每周一次"
        ],
        "answer": "季度或半年度",
        "explanation": "常见绩效考核周期为季度（OKR通常）或半年度（KPI常见）。"
      },
      {
        "id": "E39",
        "question": "'薪酬谈判'中，了解市场薪酬水平的作用是？",
        "options": [
          "直接决定员工的岗位职级",
          "确保公司薪资保持全行业最高",
          "为谈判提供合理的参考基准，确保公平竞争力和预算控制",
          "取代绩效考核的作用"
        ],
        "answer": "为谈判提供合理的参考基准，确保公平竞争力和预算控制",
        "explanation": "市场薪酬调研为薪酬谈判提供数据支撑，平衡吸引力和内部公平。"
      },
      {
        "id": "E40",
        "question": "'员工培训'按内容分类，不包括以下哪种？",
        "options": [
          "旅行培训",
          "入职培训",
          "合规培训",
          "技能培训"
        ],
        "answer": "旅行培训",
        "explanation": "员工培训按内容分包括入职培训、合规培训、技能培训、管理培训等，旅行培训不属于培训类别。"
      }
    ],
    "medium": [
      {
        "id": "M01",
        "question": "快手员工福利中，'六险一金'比'五险一金'多出的那一险通常是？",
        "options": [
          "补充医疗保险",
          "生育保险",
          "失业保险",
          "工伤保险"
        ],
        "answer": "补充医疗保险",
        "explanation": "六险一金在五险一金基础上增加补充医疗保险，提供更全面的医疗报销。"
      },
      {
        "id": "M02",
        "question": "在OKR与KPI结合使用时，两者的核心差异是什么？",
        "options": [
          "OKR关注目标方向和挑战性，KPI关注可量化的绩效指标",
          "两者完全相同",
          "OKR只用于基层",
          "KPI更有挑战性"
        ],
        "answer": "OKR关注目标方向和挑战性，KPI关注可量化的绩效指标",
        "explanation": "OKR强调目标对齐和挑战性（70%完成即优秀），KPI强调可量化达标和考核挂钩。"
      },
      {
        "id": "M03",
        "question": "HRBP模式中，HRBP与传统HR的核心区别是？",
        "options": [
          "HRBP深入业务团队作为战略伙伴，传统HR偏职能支持",
          "两者完全相同",
          "HRBP不负责招聘",
          "传统HR更深入业务"
        ],
        "answer": "HRBP深入业务团队作为战略伙伴，传统HR偏职能支持",
        "explanation": "HRBP=业务伙伴，需深入理解业务，从战略角度提供HR解决方案；传统HR偏流程执行。"
      },
      {
        "id": "M04",
        "question": "'人才盘点'中，'九宫格'模型的两个维度通常是？",
        "options": [
          "绩效和潜力",
          "薪资和工龄",
          "学历和经验",
          "年龄和性别"
        ],
        "answer": "绩效和潜力",
        "explanation": "九宫格以绩效（横轴）和潜力（纵轴）为两个维度，将人才分为9类指导发展决策。"
      },
      {
        "id": "M05",
        "question": "快手信息安全体系中，'外包人员安全管理'的核心要求是？",
        "options": [
          "外包人员需接受安全培训、签署保密协议、权限最小化",
          "外包人员不受安全管理约束",
          "外包人员享有最高权限",
          "外包人员无需签署任何协议"
        ],
        "answer": "外包人员需接受安全培训、签署保密协议、权限最小化",
        "explanation": "外包人员安全管理要求与正式员工同等的信息安全标准和更严格的权限管控。"
      },
      {
        "id": "M06",
        "question": "'劳动法规'中，经济补偿金N的计算基数是？",
        "options": [
          "劳动者解除前12个月的平均工资",
          "基本工资",
          "最低工资标准",
          "当地社平工资"
        ],
        "answer": "劳动者解除前12个月的平均工资",
        "explanation": "经济补偿金按劳动者在本单位工作年限，每满一年支付一个月工资的标准，基数为解除前12个月平均工资。"
      },
      {
        "id": "M07",
        "question": "在绩效考核中，'360度评估'的含义是？",
        "options": [
          "从上级、下属、同事、自评等多个维度进行综合评估",
          "360分满分",
          "360个指标",
          "360天评估周期"
        ],
        "answer": "从上级、下属、同事、自评等多个维度进行综合评估",
        "explanation": "360度评估从多个视角收集反馈，提供全面的绩效画像，减少单一评价者偏差。"
      },
      {
        "id": "M08",
        "question": "快手信息安全规范中，'廉正举报'机制的核心作用是？",
        "options": [
          "鼓励员工举报贪腐违规行为，维护廉洁经营环境",
          "处罚举报人",
          "收集商业情报",
          "监控竞争对手"
        ],
        "answer": "鼓励员工举报贪腐违规行为，维护廉洁经营环境",
        "explanation": "廉正举报机制为员工提供安全渠道举报贪腐、舞弊行为，保护举报人隐私。"
      },
      {
        "id": "M09",
        "question": "'职业发展'中，'双通道'晋升体系的设计是？",
        "options": [
          "管理通道和专业通道并行，技术人才不必须转管理",
          "只有管理通道",
          "只有专业通道",
          "随机晋升"
        ],
        "answer": "管理通道和专业通道并行，技术人才不必须转管理",
        "explanation": "双通道让专业人才可在技术通道晋升至与管理层同级，避免技术人才被迫转管理。"
      },
      {
        "id": "M10",
        "question": "'员工关系'管理中，'劳动仲裁'的时效是多久？",
        "options": [
          "自知道权利被侵害之日起1年",
          "6个月",
          "2年",
          "3个月"
        ],
        "answer": "自知道权利被侵害之日起1年",
        "explanation": "劳动争议申请仲裁的时效为1年，自当事人知道或应当知道权利被侵害之日起算。"
      },
      {
        "id": "M11",
        "question": "'员工培训'体系的'柯氏四级评估模型'中，第三级评估是什么？",
        "options": [
          "行为层评估（培训后行为改变）",
          "反应层评估",
          "学习层评估",
          "结果层评估"
        ],
        "answer": "行为层评估（培训后行为改变）",
        "explanation": "柯氏四级：反应层→学习层→行为层→结果层，第三级评估培训是否转化为实际行为改变。"
      },
      {
        "id": "M12",
        "question": "快手信息安全中'避免利益冲突'政策要求员工做什么？",
        "options": [
          "主动申报可能存在的利益冲突情形并回避相关决策",
          "避免所有社交活动",
          "不与外部人员沟通",
          "拒绝所有外部合作"
        ],
        "answer": "主动申报可能存在的利益冲突情形并回避相关决策",
        "explanation": "利益冲突政策要求员工主动申报，并在存在冲突时回避相关决策，确保公正性。"
      },
      {
        "id": "M13",
        "question": "'薪酬体系'设计中，内部公平性和外部竞争性的关系是？",
        "options": [
          "需平衡两者，内部公平保持激励一致性，外部竞争保障人才吸引",
          "只需内部公平",
          "只需外部竞争",
          "两者互不相关"
        ],
        "answer": "需平衡两者，内部公平保持激励一致性，外部竞争保障人才吸引",
        "explanation": "薪酬设计需同时考虑内部公平（同工同酬、内部级差合理）和外部竞争（对标市场水平吸引人才）。"
      },
      {
        "id": "M14",
        "question": "'绩效考核'中，'强制分布'制度的优缺点是？",
        "options": [
          "优点是区分度清晰，缺点是可能破坏协作和制造内部竞争",
          "优点是所有人都满意",
          "缺点是无法区分绩效",
          "完全没有优缺点"
        ],
        "answer": "优点是区分度清晰，缺点是可能破坏协作和制造内部竞争",
        "explanation": "强制分布（如2-7-1）强制区分绩效等级，但可能导致团队间恶性竞争。"
      },
      {
        "id": "M15",
        "question": "'入职流程'中，'背景调查'通常在什么阶段进行？",
        "options": [
          "发放offer前或入职前，核实候选人提供的信息真实性",
          "入职3个月后",
          "试用期内",
          "离职时"
        ],
        "answer": "发放offer前或入职前，核实候选人提供的信息真实性",
        "explanation": "背调在offer前进行，核实学历、工作经历、诚信等信息，降低招聘风险。"
      },
      {
        "id": "M16",
        "question": "快手'员工账号与权限管理'的核心原则是？",
        "options": [
          "最小权限原则，按需分配，定期审计",
          "所有人最大权限",
          "权限一经分配永不变更",
          "仅管理员有权限"
        ],
        "answer": "最小权限原则，按需分配，定期审计",
        "explanation": "权限管理遵循最小权限原则，定期审计确保权限与职责匹配。"
      },
      {
        "id": "M17",
        "question": "'校招'中的'提前批'和'正式批'的区别是？",
        "options": [
          "提前批面向更优质生源且流程更早，正式批面向所有应届生",
          "两者完全相同",
          "提前批薪资更低",
          "正式批不需要笔试"
        ],
        "answer": "提前批面向更优质生源且流程更早，正式批面向所有应届生",
        "explanation": "提前批通常在正式秋招前启动，面向目标院校优秀学生，流程更灵活。"
      },
      {
        "id": "M18",
        "question": "'试用期管理'中，试用期工资不得低于转正工资的多少？",
        "options": [
          "80%",
          "90%",
          "70%",
          "60%"
        ],
        "answer": "80%",
        "explanation": "劳动合同法规定试用期工资不得低于约定工资的80%，且不得低于当地最低工资。"
      },
      {
        "id": "M19",
        "question": "快手信息安全中'反腐败政策'的核心要求是？",
        "options": [
          "严禁商业贿赂和利益输送，建立防范和举报机制",
          "允许小额贿赂",
          "仅针对高管",
          "不需要举报机制"
        ],
        "answer": "严禁商业贿赂和利益输送，建立防范和举报机制",
        "explanation": "反腐败政策严禁任何形式的商业贿赂，建立预防、监督和举报体系。"
      },
      {
        "id": "M20",
        "question": "在'人才盘点'中，'关键人才'的识别标准通常包括？",
        "options": [
          "岗位稀缺性、绩效表现、离职影响度和市场可替代性",
          "仅看薪资水平",
          "仅看工龄",
          "仅看学历"
        ],
        "answer": "岗位稀缺性、绩效表现、离职影响度和市场可替代性",
        "explanation": "关键人才识别综合岗位重要性、个人绩效、替代难度和离职风险影响。"
      },
      {
        "id": "M21",
        "question": "'薪酬体系'中，宽带薪酬与传统等级薪酬的区别是？",
        "options": [
          "宽带薪酬同一级别薪资范围更大，更灵活适应能力差异",
          "两者完全相同",
          "宽带薪酬范围更窄",
          "传统薪酬更灵活"
        ],
        "answer": "宽带薪酬同一级别薪资范围更大，更灵活适应能力差异",
        "explanation": "宽带薪酬减少职级数量、拉大每级薪资范围，奖励能力提升而非仅晋升。"
      },
      {
        "id": "M22",
        "question": "快手信息安全中'供应商信息安全管理'要求什么？",
        "options": [
          "供应商需签署安全协议、接受安全评估、遵守数据保护要求",
          "供应商无需遵守信息安全要求",
          "供应商享有豁免权",
          "仅需口头约定"
        ],
        "answer": "供应商需签署安全协议、接受安全评估、遵守数据保护要求",
        "explanation": "供应商安全管理要求第三方供应商在数据处理和安全上达到同等标准。"
      },
      {
        "id": "M23",
        "question": "'离职管理'中，'离职率'的计算公式是？",
        "options": [
          "离职人数除以平均在职人数",
          "离职人数除以年初人数",
          "离职人数除以新入职人数",
          "离职人数除以总人数"
        ],
        "answer": "离职人数除以平均在职人数",
        "explanation": "离职率=期间离职人数/（期初人数+期末人数）/2，即平均在职人数。"
      },
      {
        "id": "M24",
        "question": "'EAP'（员工帮助计划）通常提供哪些服务？",
        "options": [
          "心理咨询、法律援助、财务咨询、危机干预",
          "仅提供健身服务",
          "仅提供法律援助",
          "仅提供职业规划"
        ],
        "answer": "心理咨询、法律援助、财务咨询、危机干预",
        "explanation": "EAP是综合性员工支持服务，涵盖心理、法律、财务等多方面。"
      },
      {
        "id": "M25",
        "question": "在'文化建设'中，'价值观行为化'的含义是？",
        "options": [
          "将抽象价值观转化为具体可观察、可评估的行为标准",
          "只喊口号",
          "价值观与行为无关",
          "仅用于招聘"
        ],
        "answer": "将抽象价值观转化为具体可观察、可评估的行为标准",
        "explanation": "价值观行为化让价值观落地，例如'坦诚清晰'行为化为'及时反馈不同意见'等具体行为。"
      },
      {
        "id": "M26",
        "question": "快手'物理与环境安全管理'的核心内容是？",
        "options": [
          "保障办公场所和设备物理安全，防止未授权访问和物理损害",
          "物理锻炼安全管理",
          "环境保护政策",
          "物理学科研究"
        ],
        "answer": "保障办公场所和设备物理安全，防止未授权访问和物理损害",
        "explanation": "物理与环境安全管理包括门禁控制、监控、设备防护、灾备等。"
      },
      {
        "id": "M27",
        "question": "'HRBP模式'中，'三支柱模型'的三个角色是？",
        "options": [
          "COE（专家中心）、HRBP（业务伙伴）、SSC（共享服务中心）",
          "招聘、薪酬、培训",
          "CEO、CFO、CHRO",
          "战略HR、运营HR、技术HR"
        ],
        "answer": "COE（专家中心）、HRBP（业务伙伴）、SSC（共享服务中心）",
        "explanation": "三支柱模型：COE做战略和方案设计，HRBP做业务落地，SSC做标准化事务处理。"
      },
      {
        "id": "M28",
        "question": "快手'数据安全管理'的核心原则包括？",
        "options": [
          "数据分类分级、最小必要原则、加密传输和存储",
          "数据全部公开",
          "数据不需要管理",
          "仅加密存储"
        ],
        "answer": "数据分类分级、最小必要原则、加密传输和存储",
        "explanation": "数据安全管理要求对数据进行分类分级保护，遵循最小必要原则，确保加密传输存储。"
      },
      {
        "id": "M29",
        "question": "'员工满意度'调查中，eNPS指标的含义是？",
        "options": [
          "员工净推荐值，衡量员工愿意推荐公司作为工作场所的程度",
          "电子化绩效系统",
          "员工净利润分享",
          "员工数量指标"
        ],
        "answer": "员工净推荐值，衡量员工愿意推荐公司作为工作场所的程度",
        "explanation": "eNPS=推荐者%-贬损者%，范围-100到100，反映员工整体忠诚度和满意度。"
      },
      {
        "id": "M30",
        "question": "'薪酬谈判'中，'Total Package'策略的核心是？",
        "options": [
          "展示整体薪酬包（基本+绩效+股权+福利）的总价值而非仅谈基本工资",
          "只谈基本工资",
          "只谈股权",
          "只谈福利"
        ],
        "answer": "展示整体薪酬包（基本+绩效+股权+福利）的总价值而非仅谈基本工资",
        "explanation": "Total Package强调综合回报，让候选人看到完整价值，增强吸引力。"
      },
      {
        "id": "M31",
        "question": "快手'安全事件应急响应'流程通常包括哪些步骤？",
        "options": [
          "发现→上报→分析→处置→恢复→复盘",
          "仅需上报",
          "仅需处置",
          "忽略即可"
        ],
        "answer": "发现→上报→分析→处置→恢复→复盘",
        "explanation": "应急响应遵循标准流程：及时发现、快速上报、根因分析、有效处置、系统恢复、总结复盘。"
      },
      {
        "id": "M32",
        "question": "'股权激励'中，期权的'归属期'（Vesting Schedule）通常设计为？",
        "options": [
          "4年归属，1年悬崖期（Cliff），之后按月归属",
          "一次性全部归属",
          "2年全部归属",
          "无归属期限制"
        ],
        "answer": "4年归属，1年悬崖期（Cliff），之后按月归属",
        "explanation": "典型期权归属：4年期，1年悬崖（满1年获25%），之后按月归属1/48。"
      },
      {
        "id": "M33",
        "question": "快手'日志管理'的核心要求是？",
        "options": [
          "操作日志留存、可追溯、防篡改、定期审计",
          "不需要日志",
          "日志可以随意修改",
          "仅记录错误日志"
        ],
        "answer": "操作日志留存、可追溯、防篡改、定期审计",
        "explanation": "日志管理确保操作可追溯，日志防篡改，为安全审计提供依据。"
      },
      {
        "id": "M34",
        "question": "'团队建设'中，'心理安全感'的含义是？",
        "options": [
          "团队成员相信可以自由表达观点和犯错而不会受到惩罚",
          "物理安全感",
          "团队没有冲突",
          "所有人都意见一致"
        ],
        "answer": "团队成员相信可以自由表达观点和犯错而不会受到惩罚",
        "explanation": "心理安全感是高绩效团队的核心特征，Google研究发现它是团队成功的关键因素。"
      },
      {
        "id": "M35",
        "question": "快手'隐私保护规范'的核心要求是？",
        "options": [
          "收集个人信息需明确告知并获同意，最小必要收集，保障用户隐私权",
          "不需要用户同意",
          "收集所有信息",
          "隐私保护不重要"
        ],
        "answer": "收集个人信息需明确告知并获同意，最小必要收集，保障用户隐私权",
        "explanation": "隐私保护遵循告知同意原则和最小必要原则，保障个人信息安全。"
      },
      {
        "id": "M36",
        "question": "'员工关系'中，'非自愿离职'的法律风险主要在于？",
        "options": [
          "违法解除需支付双倍经济补偿金（2N），还可能被要求恢复劳动关系",
          "无风险",
          "仅需支付N",
          "仅需口头通知"
        ],
        "answer": "违法解除需支付双倍经济补偿金（2N），还可能被要求恢复劳动关系",
        "explanation": "违法解除劳动合同的后果是支付赔偿金2N，劳动者还可选择要求继续履行合同。"
      },
      {
        "id": "M37",
        "question": "快手'系统开发维护安全管理'中，'安全左移'的含义是？",
        "options": [
          "在开发早期就融入安全措施，而非上线后才补漏洞",
          "安全团队坐在左边",
          "只做上线安全检测",
          "安全检查不重要"
        ],
        "answer": "在开发早期就融入安全措施，而非上线后才补漏洞",
        "explanation": "安全左移将安全测试融入需求、设计、开发各阶段，降低安全漏洞修复成本。"
      },
      {
        "id": "M38",
        "question": "'绩效考核'中，'目标管理'（MBO）与OKR的关系是？",
        "options": [
          "OKR是MBO的演进版本，更强调对齐和挑战性，弱化考核挂钩",
          "两者完全矛盾",
          "MBO已完全淘汰",
          "OKR不设目标"
        ],
        "answer": "OKR是MBO的演进版本，更强调对齐和挑战性，弱化考核挂钩",
        "explanation": "OKR继承了MBO目标管理的核心理念，但强调透明对齐、挑战性和解耦绩效考核。"
      },
      {
        "id": "M39",
        "question": "快手'漏洞处理规范'中，漏洞严重等级通常如何划分？",
        "options": [
          "按CVSS评分分为严重、高危、中危、低危",
          "只分高低两档",
          "无需分级",
          "按发现时间排序"
        ],
        "answer": "按CVSS评分分为严重、高危、中危、低危",
        "explanation": "漏洞按CVSS（通用漏洞评分系统）分级，不同等级对应不同响应时效。"
      },
      {
        "id": "M40",
        "question": "'职业发展'中，IDP的含义和作用是？",
        "options": [
          "Individual Development Plan（个人发展计划），规划个人成长路径和行动",
          "Internal Data Platform",
          "Integrated Design Process",
          "International Development Program"
        ],
        "answer": "Individual Development Plan（个人发展计划），规划个人成长路径和行动",
        "explanation": "IDP是员工与上级共同制定的发展计划，明确目标、差距和具体提升行动。"
      }
    ],
    "hard": [
      {
        "id": "H01",
        "question": "在HRBP三支柱模型中，COE和SSC的职责边界如何划分？",
        "options": [
          "COE负责战略方案设计，SSC负责标准化事务处理，HRBP负责业务落地衔接",
          "三者职责完全相同",
          "COE负责事务处理",
          "SSC负责战略设计"
        ],
        "answer": "COE负责战略方案设计，SSC负责标准化事务处理，HRBP负责业务落地衔接",
        "explanation": "COE=方案设计专家，SSC=事务执行（入转调离/发薪等），HRBP=业务理解+方案落地。"
      },
      {
        "id": "H02",
        "question": "快手'信息系统安全检查与审计'的审计周期和内容是？",
        "options": [
          "定期全面审计加专项审计，覆盖制度合规、技术控制、操作流程",
          "仅年度审计",
          "无需审计",
          "仅审计财务数据"
        ],
        "answer": "定期全面审计加专项审计，覆盖制度合规、技术控制、操作流程",
        "explanation": "安全审计包括定期全面审计和事件驱动的专项审计，覆盖管理和技术两个层面。"
      },
      {
        "id": "H03",
        "question": "在'人才盘点'九宫格中，'高绩效低潜力'人才的管理策略是？",
        "options": [
          "保持当前岗位贡献，给予认可奖励，不强求晋升",
          "重点培养",
          "优先淘汰",
          "强制转岗"
        ],
        "answer": "保持当前岗位贡献，给予认可奖励，不强求晋升",
        "explanation": "高绩效低潜力（专家型）人才在当前岗位持续贡献高价值，不宜强制推进管理线。"
      },
      {
        "id": "H04",
        "question": "'股权激励'中，'行权价'的确定依据是什么（以上市公司为例）？",
        "options": [
          "不低于公允价值的公平市场价格，通常为期权授予时股价或评估价",
          "随意定价",
          "固定为1元",
          "按最高股价确定"
        ],
        "answer": "不低于公允价值的公平市场价格，通常为期权授予时股价或评估价",
        "explanation": "行权价需符合公允性原则，上市公司通常不低于授予日收盘价或一段时间均价。"
      },
      {
        "id": "H05",
        "question": "'薪酬体系'中，'岗位价值评估'的常用方法不包括？",
        "options": [
          "360度评估法",
          "海氏评估法",
          "美世IPE法",
          "要素计点法"
        ],
        "answer": "360度评估法",
        "explanation": "岗位价值评估方法包括海氏法、美世IPE、要素计点法等，360度是绩效评估方法。"
      },
      {
        "id": "H06",
        "question": "在'劳动法规'中，竞业限制协议的有效条件不包括？",
        "options": [
          "无需支付补偿金即可生效",
          "限制范围合理",
          "补偿金不低于法定标准",
          "期限不超过2年"
        ],
        "answer": "无需支付补偿金即可生效",
        "explanation": "竞业限制生效需同时满足：合理范围、补偿金（不低于平均工资30%）、期限≤2年。"
      },
      {
        "id": "H07",
        "question": "'绩效考核'中，'校准会议'（Calibration Session）的核心作用是？",
        "options": [
          "消除不同管理者评分标准差异，确保绩效评定的一致性和公平性",
          "校准机器精度",
          "统一所有人的评分",
          "降低绩效分数"
        ],
        "answer": "消除不同管理者评分标准差异，确保绩效评定的一致性和公平性",
        "explanation": "校准会议让管理者对比讨论，确保跨团队绩效标准一致，避免'宽严偏差'。"
      },
      {
        "id": "H08",
        "question": "快手'人员信息安全'要求中，员工离职后的安全措施包括？",
        "options": [
          "及时回收权限、设备，撤销账号，数据清除，保密义务延续",
          "保留所有权限",
          "不回收设备",
          "无任何措施"
        ],
        "answer": "及时回收权限、设备，撤销账号，数据清除，保密义务延续",
        "explanation": "离职安全措施包括权限回收、设备收回、账号注销、保密协议持续有效。"
      },
      {
        "id": "H09",
        "question": "'薪酬谈判'中，'锚定效应'如何影响谈判结果？",
        "options": [
          "先提出的数字会成为谈判锚点，后续讨论围绕该锚点调整",
          "锚定效应不影响谈判",
          "只能向上调整",
          "锚点必须是市场价"
        ],
        "answer": "先提出的数字会成为谈判锚点，后续讨论围绕该锚点调整",
        "explanation": "锚定效应使先提出的数字（高或低）显著影响最终结果，薪酬谈判需善用此心理效应。"
      },
      {
        "id": "H10",
        "question": "在'OKR设定'中，OKR与绩效考核'解耦'的核心原因是？",
        "options": [
          "避免员工因考核压力设低目标，确保OKR保持挑战性和创新性",
          "降低管理成本",
          "OKR不需要评估",
          "绩效考核已废除"
        ],
        "answer": "避免员工因考核压力设低目标，确保OKR保持挑战性和创新性",
        "explanation": "OKR与绩效解耦让员工敢于设高目标（70%即优秀），若强挂钩则倾向于设必达目标。"
      },
      {
        "id": "H11",
        "question": "快手ESG三级治理结构中，最顶层的治理机构是？",
        "options": [
          "董事会层面的Corporate Governance Committee",
          "CEO办公室",
          "HR部门",
          "业务线负责人"
        ],
        "answer": "董事会层面的Corporate Governance Committee",
        "explanation": "ESG三级治理：董事会级公司治理委员会→管理层ESG委员会→执行层工作组。"
      },
      {
        "id": "H12",
        "question": "'员工培训'中，'70-20-10'学习模型的含义是？",
        "options": [
          "70%来自实践、20%来自他人反馈、10%来自正式培训",
          "培训预算分配比例",
          "培训时间安排",
          "考核分数占比"
        ],
        "answer": "70%来自实践、20%来自他人反馈、10%来自正式培训",
        "explanation": "70-20-10模型表明成人学习主要来自工作实践，其次来自人际互动，正式培训仅占10%。"
      },
      {
        "id": "H13",
        "question": "在'HRBP模式'中，HRBP'懂业务'的具体标准是？",
        "options": [
          "理解业务战略、痛点、关键指标和组织能力差距，能用HR方案解决业务问题",
          "只需要知道业务名称",
          "了解产品功能即可",
          "和业务团队一起加班"
        ],
        "answer": "理解业务战略、痛点、关键指标和组织能力差距，能用HR方案解决业务问题",
        "explanation": "HRBP的'懂业务'指能从组织视角诊断业务问题并设计HR解决方案，而非仅了解表面信息。"
      },
      {
        "id": "H14",
        "question": "快手'信息安全'中，'安全事件应急响应'的SLA要求通常是什么？",
        "options": [
          "严重漏洞需在24小时内响应处置，高危72小时内，中危7天内",
          "所有漏洞1年内处理",
          "无需响应时效要求",
          "仅在工作时间处理"
        ],
        "answer": "严重漏洞需在24小时内响应处置，高危72小时内，中危7天内",
        "explanation": "安全事件根据等级设定不同响应SLA，严重等级越高时效要求越严。"
      },
      {
        "id": "H15",
        "question": "'人才盘点'中，'人才密度'概念的含义是？",
        "options": [
          "单位组织内高绩效高潜力人才的占比比例",
          "员工人数密度",
          "办公区域人员密度",
          "薪资密度"
        ],
        "answer": "单位组织内高绩效高潜力人才的占比比例",
        "explanation": "人才密度=高绩效高潜力人才/总人数，密度越高组织创新能力越强。"
      },
      {
        "id": "H16",
        "question": "'离职管理'中，'离职预测模型'通常使用什么数据构建？",
        "options": [
          "考勤异常、薪资竞争力、晋升停滞、满意度下降、市场活跃度等多维特征",
          "仅离职率数据",
          "仅工龄数据",
          "随机猜测"
        ],
        "answer": "考勤异常、薪资竞争力、晋升停滞、满意度下降、市场活跃度等多维特征",
        "explanation": "离职预测模型通过多维行为和态度数据，识别高风险离职人群以提前干预。"
      },
      {
        "id": "H17",
        "question": "快手'员工账号与权限管理'中，'特权账号管理'的核心要求是？",
        "options": [
          "特权账号最小化、双人审批、操作审计、定期复核",
          "特权账号不受限制",
          "仅管理员可使用特权账号",
          "特权账号无需审计"
        ],
        "answer": "特权账号最小化、双人审批、操作审计、定期复核",
        "explanation": "特权账号（root/admin）管理最严格：最小化数量、审批使用、全量审计、定期清理。"
      },
      {
        "id": "H18",
        "question": "'股权激励'中，'限制性股票'和'期权'的核心区别是？",
        "options": [
          "限制性股票先获股后受限，期权先获权后行权",
          "两者完全相同",
          "期权风险更低",
          "限制性股票不需要归属期"
        ],
        "answer": "限制性股票先获股后受限，期权先获权后行权",
        "explanation": "限制性股票=先授予股票但有出售限制；期权=先给未来以约定价格购买的权利。"
      },
      {
        "id": "H19",
        "question": "在'文化建设'中，'文化落地'最有效的手段是什么？",
        "options": [
          "将价值观融入招聘筛选、绩效评估、晋升决策等核心管理流程",
          "仅靠宣传标语",
          "年会上墙",
          "喊口号"
        ],
        "answer": "将价值观融入招聘筛选、绩效评估、晋升决策等核心管理流程",
        "explanation": "文化落地的关键是将价值观嵌入制度流程，形成'招-考-升-离'全链条的行为引导。"
      },
      {
        "id": "H20",
        "question": "快手ESG公益使命'科技连接善意'下的项目不包括？",
        "options": [
          "员工年终奖发放",
          "幸福大讲堂",
          "启智未来学堂",
          "非遗传习学堂"
        ],
        "answer": "员工年终奖发放",
        "explanation": "ESG公益项目包括幸福大讲堂、启智未来学堂、非遗传习学堂等，年终奖不属于公益项目。"
      },
      {
        "id": "H21",
        "question": "'薪酬体系'中，'内部薪酬比'（Compa-ratio）的含义是？",
        "options": [
          "实际薪资与薪资范围中位值的比值",
          "最高薪资与最低薪资的比",
          "基本薪资与绩效薪资的比",
          "内部薪资与外部薪资的比"
        ],
        "answer": "实际薪资与薪资范围中位值的比值",
        "explanation": "Compa-ratio=实际薪资/薪资范围中位值，1.0表示恰在中位值，用于判断薪资定位。"
      },
      {
        "id": "H22",
        "question": "快手2022年ESG报告中，带动就业人数为？",
        "options": [
          "3621万",
          "1000万",
          "500万",
          "1亿"
        ],
        "answer": "3621万",
        "explanation": "2022年快手带动就业3621万人。"
      },
      {
        "id": "H23",
        "question": "'员工关系'中，'集体合同'与'劳动合同'的效力关系是？",
        "options": [
          "集体合同标准不低于法定最低，劳动合同标准不低于集体合同",
          "集体合同效力更高",
          "劳动合同效力更高",
          "两者无关联"
        ],
        "answer": "集体合同标准不低于法定最低，劳动合同标准不低于集体合同",
        "explanation": "效力层级：法律>集体合同>劳动合同，劳动合同约定不得低于集体合同标准。"
      },
      {
        "id": "H24",
        "question": "在'绩效考核'中，'归因偏差'对评价的影响是？",
        "options": [
          "评价者将成功归于自身因素、失败归于外部因素，导致评价不客观",
          "归因偏差不影响评价",
          "只影响被评价者",
          "只影响自评"
        ],
        "answer": "评价者将成功归于自身因素、失败归于外部因素，导致评价不客观",
        "explanation": "归因偏差使管理者倾向将团队成功归于自己的领导、失败归于员工能力，造成评价偏差。"
      },
      {
        "id": "H25",
        "question": "快手'外包人员安全管理'与正式员工安全管理的核心差异是？",
        "options": [
          "外包人员权限更受限、数据访问范围更窄、设备管理更严格",
          "外包人员安全管理更宽松",
          "完全相同管理标准",
          "外包人员不需要安全管理"
        ],
        "answer": "外包人员权限更受限、数据访问范围更窄、设备管理更严格",
        "explanation": "外包人员因劳动关系不在公司，安全管控需更严格：更窄权限、更严格设备管理和数据隔离。"
      },
      {
        "id": "H26",
        "question": "'职业发展'中，'彼得原理'对组织管理的启示是？",
        "options": [
          "人会被晋升到不胜任的层级，组织需提供专业通道避免不胜任晋升",
          "晋升总是正确的",
          "人应该不断晋升",
          "能力与职级始终匹配"
        ],
        "answer": "人会被晋升到不胜任的层级，组织需提供专业通道避免不胜任晋升",
        "explanation": "彼得原理指人因在原岗位优秀被晋升，最终到达不胜任的层级。双通道可缓解此问题。"
      },
      {
        "id": "H27",
        "question": "'员工满意度'调查中，影响eNPS的关键驱动因素通常包括？",
        "options": [
          "直属上级管理质量、职业发展机会、工作意义感、薪酬竞争力",
          "仅薪酬因素",
          "仅工作环境",
          "仅人际关系"
        ],
        "answer": "直属上级管理质量、职业发展机会、工作意义感、薪酬竞争力",
        "explanation": "研究表明直属上级是员工满意度最大单一影响因素，其次是发展和意义感。"
      },
      {
        "id": "H28",
        "question": "在'薪酬体系'设计中，'薪资重叠'（Overlap）的目的和风险是什么？",
        "options": [
          "目的允许相邻级别薪资交叉激励能力成长，风险是级差模糊降低晋升激励",
          "重叠无任何目的",
          "重叠无风险",
          "目的仅是降低成本"
        ],
        "answer": "目的允许相邻级别薪资交叉激励能力成长，风险是级差模糊降低晋升激励",
        "explanation": "适度重叠让高绩效低级别员工薪资超过低高级别，但过度重叠削弱晋升吸引力。"
      },
      {
        "id": "H29",
        "question": "快手'漏洞处理规范'中，零日漏洞（0-day）的定义是？",
        "options": [
          "已被发现但尚未公开或补丁尚未发布的漏洞",
          "发布1天内发现的漏洞",
          "每100天出现的漏洞",
          "每天0点出现的漏洞"
        ],
        "answer": "已被发现但尚未公开或补丁尚未发布的漏洞",
        "explanation": "零日漏洞指已被发现但厂商尚不知情或无补丁的漏洞，利用风险极高。"
      },
      {
        "id": "H30",
        "question": "'HRBP模式'中，SSC（共享服务中心）的运营效率指标通常包括？",
        "options": [
          "处理时效、首次解决率、差错率、成本效率、员工满意度",
          "仅成本指标",
          "仅员工满意度",
          "仅处理数量"
        ],
        "answer": "处理时效、首次解决率、差错率、成本效率、员工满意度",
        "explanation": "SSC作为服务中心需追踪全维度运营指标：效率（时效/解决率）、质量（差错率）、成本和体验。"
      },
      {
        "id": "H31",
        "question": "在'试用期管理'中，用人单位以'不符合录用条件'解除合同需满足什么条件？",
        "options": [
          "须有明确的录用条件且已告知员工，并有证据证明不符合",
          "无需任何条件",
          "仅需口头说明",
          "员工同意即可"
        ],
        "answer": "须有明确的录用条件且已告知员工，并有证据证明不符合",
        "explanation": "合法解除须三要素：有明确录用条件、已事先告知员工、有客观证据证明不符合。"
      },
      {
        "id": "H32",
        "question": "'股权激励'的会计处理中，期权费用的确认方式是？",
        "options": [
          "在归属期内按公允价值分期确认费用，不等到行权时一次性确认",
          "行权时一次性确认",
          "不需要确认费用",
          "仅在授予日确认"
        ],
        "answer": "在归属期内按公允价值分期确认费用，不等到行权时一次性确认",
        "explanation": "按IFRS/CAS准则，期权费用在归属期内分期确认（Black-Scholes或二叉树模型估值）。"
      },
      {
        "id": "H33",
        "question": "快手'隐私保护规范'中，'数据最小必要原则'在招聘环节的具体应用是？",
        "options": [
          "仅收集岗位相关的必要信息，不强制收集与履职无关的敏感个人信息",
          "收集所有个人信息",
          "不收集任何信息",
          "仅收集身份证号码"
        ],
        "answer": "仅收集岗位相关的必要信息，不强制收集与履职无关的敏感个人信息",
        "explanation": "最小必要原则要求招聘中仅收集必要信息（学历/经历），不应强制收集婚育等敏感信息。"
      },
      {
        "id": "H34",
        "question": "'人才盘点'中，'继任计划'（Succession Planning）的关键成功因素是？",
        "options": [
          "高层参与、制度化流程、多候选人储备、发展性而非替代性思维",
          "仅需名单",
          "仅关注现任高管",
          "无需流程"
        ],
        "answer": "高层参与、制度化流程、多候选人储备、发展性而非替代性思维",
        "explanation": "成功的继任计划需CEO主导、流程制度化、每个关键岗位有2-3名候选人储备。"
      },
      {
        "id": "H35",
        "question": "'员工关系'中，'事实劳动关系'的法律认定标准是？",
        "options": [
          "存在用工管理、报酬发放、业务从属等实质要素，即使未签书面合同",
          "必须有书面合同",
          "仅凭口头约定",
          "仅需社保缴纳记录"
        ],
        "answer": "存在用工管理、报酬发放、业务从属等实质要素，即使未签书面合同",
        "explanation": "事实劳动关系看实质：有管理服从关系、报酬支付、工作属单位业务组成部分。"
      },
      {
        "id": "H36",
        "question": "快手'安全事件应急响应'中，'零信任'安全模型的核心原则是？",
        "options": [
          "从不信任，始终验证，默认拒绝，最小权限",
          "信任内部网络",
          "仅需密码认证",
          "仅对外部威胁验证"
        ],
        "answer": "从不信任，始终验证，默认拒绝，最小权限",
        "explanation": "零信任放弃'内网可信'假设，所有访问请求均需验证身份和权限，不论来源。"
      },
      {
        "id": "H37",
        "question": "'绩效考核'中，'递延效应'（Halo/Horn Effect）如何影响评价？",
        "options": [
          "评价者因某一方面好/坏印象而泛化到所有维度，导致全面高估或低估",
          "递延效应提高评价准确性",
          "仅影响自评",
          "没有影响"
        ],
        "answer": "评价者因某一方面好/坏印象而泛化到所有维度，导致全面高估或低估",
        "explanation": "光环/恶魔效应使管理者因员工某一突出特征影响对所有维度的评价，需校准会议纠正。"
      },
      {
        "id": "H38",
        "question": "在'员工培训'ROI评估中，Phillips五级模型比柯氏四级多了什么？",
        "options": [
          "第五级：投资回报率（ROI），量化培训的财务收益",
          "多了一级考试",
          "多了一级问卷",
          "没有区别"
        ],
        "answer": "第五级：投资回报率（ROI），量化培训的财务收益",
        "explanation": "Phillips模型在柯氏四级基础上增加ROI级，将培训收益转化为货币价值与成本比较。"
      },
      {
        "id": "H39",
        "question": "快手'数据安全管理'中，'数据分类分级'的分级通常包括？",
        "options": [
          "公开、内部、敏感、机密等不同等级",
          "只分公开和秘密两档",
          "不分等级",
          "仅按部门分类"
        ],
        "answer": "公开、内部、敏感、机密等不同等级",
        "explanation": "数据分级通常为：公开→内部→敏感→机密→绝密，不同等级对应不同的保护措施。"
      },
      {
        "id": "H40",
        "question": "'文化建设'中，'亚文化冲突'的典型表现和解决方法是？",
        "options": [
          "不同团队形成相悖的工作习惯和价值观，需通过跨团队轮岗和共建规范来对齐",
          "亚文化冲突无法解决",
          "亚文化冲突是好事",
          "强制统一所有行为"
        ],
        "answer": "不同团队形成相悖的工作习惯和价值观，需通过跨团队轮岗和共建规范来对齐",
        "explanation": "亚文化冲突常见于快速扩张组织，需通过人员流动、制度共建和价值观重申来化解。"
      }
    ]
  }
}